image_processing_1210/__init__.py
image_processing_1210/processing/__init__.py
image_processing_1210/processing/combination.py
image_processing_1210/processing/transformation.py
image_processing_1210/utils/__init__.py
image_processing_1210/utils/io.py
image_processing_1210/utils/plot.py
image_processing_1210-0.0.1.dist-info/METADATA
image_processing_1210-0.0.1.dist-info/WHEEL
image_processing_1210-0.0.1.dist-info/top_level.txt
image_processing_1210-0.0.1.dist-info/RECORD
