Metadata-Version: 2.1
Name: image_processing_1210
Version: 0.0.1
Summary: Image Processing Package using Skimage
Home-page: https://github.com/SergioMCavalcante/image-processing-1210
Author: SMC
Requires-Python: >=3.5
Requires-Dist: matplotlib
Requires-Dist: numpy
Requires-Dist: scikit-image >=0.16.1
